<annotation>
	<folder>fire_new</folder>
	<filename>fire_me10.jpg</filename>
	<path>C:\Users\HP\Desktop\fire_new\fire_me10.jpg</path>
	<source>
		<database>Unknown</database>
	</source>
	<size>
		<width>600</width>
		<height>600</height>
		<depth>3</depth>
	</size>
	<segmented>0</segmented>
	<object>
		<name>fire</name>
		<pose>Unspecified</pose>
		<truncated>0</truncated>
		<difficult>0</difficult>
		<bndbox>
			<xmin>102</xmin>
			<ymin>130</ymin>
			<xmax>515</xmax>
			<ymax>299</ymax>
		</bndbox>
	</object>
	<object>
		<name>fire</name>
		<pose>Unspecified</pose>
		<truncated>0</truncated>
		<difficult>0</difficult>
		<bndbox>
			<xmin>305</xmin>
			<ymin>307</ymin>
			<xmax>374</xmax>
			<ymax>456</ymax>
		</bndbox>
	</object>
	<object>
		<name>fire</name>
		<pose>Unspecified</pose>
		<truncated>0</truncated>
		<difficult>0</difficult>
		<bndbox>
			<xmin>18</xmin>
			<ymin>244</ymin>
			<xmax>99</xmax>
			<ymax>334</ymax>
		</bndbox>
	</object>
	<object>
		<name>fire</name>
		<pose>Unspecified</pose>
		<truncated>0</truncated>
		<difficult>0</difficult>
		<bndbox>
			<xmin>221</xmin>
			<ymin>302</ymin>
			<xmax>287</xmax>
			<ymax>332</ymax>
		</bndbox>
	</object>
	<object>
		<name>fire</name>
		<pose>Unspecified</pose>
		<truncated>0</truncated>
		<difficult>0</difficult>
		<bndbox>
			<xmin>447</xmin>
			<ymin>300</ymin>
			<xmax>512</xmax>
			<ymax>358</ymax>
		</bndbox>
	</object>
</annotation>
